MANIFEST.in
README.rst
setup.py
brunel/D3_Template.html
brunel/D3_Template.js
brunel/__init__.py
brunel/brunel_main.py
brunel/brunel_util.py
brunel/magics.py
brunel.egg-info/PKG-INFO
brunel.egg-info/SOURCES.txt
brunel.egg-info/dependency_links.txt
brunel.egg-info/requires.txt
brunel.egg-info/top_level.txt
brunel/brunel_ext/brunel.2.6.css
brunel/brunel_ext/brunel.2.6.min.js
brunel/brunel_ext/brunel.controls.2.6.min.js
brunel/brunel_ext/sumoselect/jquery.sumoselect.min.js
brunel/brunel_ext/sumoselect/sumoselect.css
brunel/lib/brunel-core-2.6.jar
brunel/lib/brunel-data-2.6.jar
brunel/lib/gson-2.3.1.jar