Metadata-Version: 1.1
Name: brunel
Version: 2.6.2
Summary: Brunel Visualization For Jupyter/IPython Notebooks
Home-page: UNKNOWN
Author: UNKNOWN
Author-email: UNKNOWN
License: Apache Software License 2.0
Keywords: visualization,grammar of graphics
Platform: UNKNOWN
Classifier: License :: OSI Approved :: Apache Software License
Classifier: Development Status :: 4 - Beta
Classifier: Programming Language :: Python :: 2
Classifier: Programming Language :: Python :: 3
